torchtops/__init__.py
torchtops/layer_profiler.py
torchtops/utils.py
torchtops-0.1.2.dist-info/LICENSE
torchtops-0.1.2.dist-info/METADATA
torchtops-0.1.2.dist-info/WHEEL
torchtops-0.1.2.dist-info/top_level.txt
torchtops-0.1.2.dist-info/RECORD
